{
 "number": 1047,
 "image_url": "https://algonfts.art/ALGUZQKNPJIU2GMACAMESXTAVBLGCJEVGAYCGZEMKWI4QRPKV3EDTTSQNM/1/1676494011169.webp",
 "metadata_cid": "bafkreidmazxuejbb2b6eblrrchxrjzbdm6r3qvke5zivfum2eug6pq6guy",
 "metadata": {
  "name": "Algonean #1047",
  "standard": "arc3",
  "image": "ipfs://bafkreic7tuwgxprpq6u6dic636oy3lhahlbryago6neo55djnlednbf4z4",
  "image_mime_type": "image/webp",
  "properties": {
   "Background": "Notebook",
   "Bodysuit": "Plushy Melon",
   "Face": "Serene Purple",
   "Feet": "Mint Hikers",
   "Hands": "Blue Biker",
   "Head": "Blue Gumball",
   "Item 1": "Blue Boomerang",
   "Item 2": "Cassette",
   "Outfit": "Green Jersey",
   "Special": "None"
  }
 }
}