{
 "number": 1058,
 "image_url": "https://algonfts.art/ALGUZQKNPJIU2GMACAMESXTAVBLGCJEVGAYCGZEMKWI4QRPKV3EDTTSQNM/1/1676055883295.webp",
 "metadata_cid": "bafkreigobowqdwfhkbvrdnjfeju4tbqtizpqm4rzzithhd7e2rzmtpeoi4",
 "metadata": {
  "name": "Algonean #1058",
  "standard": "arc3",
  "image": "ipfs://bafybeiggkwj63fasews4fga7llygycektlh5rqtpocyskkfyenvqbje45q",
  "image_mime_type": "image/webp",
  "properties": {
   "Background": "Pink Dream",
   "Bodysuit": "Glossy Bubblegum",
   "Face": "Angry Orange",
   "Feet": "Gray Tigers",
   "Hands": "Purple Hazmat",
   "Head": "Blonde Bun",
   "Item 1": "Red Blurby",
   "Item 2": "None",
   "Outfit": "Green Jersey",
   "Special": "Green Power Chord Tail"
  }
 }
}