{
 "number": 1097,
 "image_url": "https://algonfts.art/ALGUZQKNPJIU2GMACAMESXTAVBLGCJEVGAYCGZEMKWI4QRPKV3EDTTSQNM/1/1676056046606.webp",
 "metadata_cid": "bafkreifady7qvm32vkwjqybb7nt7zhwbcixyzufcp632lox5pl3k3tjzxa",
 "metadata": {
  "name": "Algonean #1097",
  "standard": "arc3",
  "image": "ipfs://bafybeie4ddt2hvcb3oro3pkhbxden5wibtga4mjvlw2zsg5hkdrlgh6pfq",
  "image_mime_type": "image/webp",
  "properties": {
   "Background": "Honeycomb",
   "Bodysuit": "Moss",
   "Face": "Scared Purple",
   "Feet": "Gray Workers",
   "Hands": "Graphite",
   "Head": "Frozen Brain",
   "Item 1": "Blue Racket",
   "Item 2": "Pillow",
   "Outfit": "Green Vibe",
   "Special": "None"
  }
 }
}