{
 "number": 1327,
 "image_url": "https://algonfts.art/ALGUZQKNPJIU2GMACAMESXTAVBLGCJEVGAYCGZEMKWI4QRPKV3EDTTSQNM/1/1676134090950.webp",
 "metadata_cid": "bafkreignfingxb7enhp2tosvnqmvg74r67fto5qw33ayqip45v6rbxz52u",
 "metadata": {
  "name": "Algonean #1327",
  "standard": "arc3",
  "image": "ipfs://bafkreidh7baw2av7twai2shry36kfjocexzau7zwqkmazwxwl2kwsk6oty",
  "image_mime_type": "image/webp",
  "properties": {
   "Background": "Tangerine",
   "Bodysuit": "Glossy Jade",
   "Face": "High Green",
   "Feet": "Red Oldies",
   "Hands": "Raven",
   "Head": "None",
   "Item 1": "Machete",
   "Item 2": "Blue Paddleball",
   "Outfit": "Gray Junior",
   "Special": "None"
  }
 }
}