{
 "number": 1358,
 "image_url": "https://algonfts.art/ALGUZQKNPJIU2GMACAMESXTAVBLGCJEVGAYCGZEMKWI4QRPKV3EDTTSQNM/1/1676057977059.webp",
 "metadata_cid": "bafkreig7grqsqlzd6hp5wstz2lvdjqgaxr5plvdub6wb6edgzgxkk32pgy",
 "metadata": {
  "name": "Algonean #1358",
  "standard": "arc3",
  "image": "ipfs://bafkreibkswegtuybwg53hojqrhxlfzittsgirhlz4zhwemcd2ccgoftiyi",
  "image_mime_type": "image/webp",
  "properties": {
   "Background": "Orange",
   "Bodysuit": "Rundown Lavender",
   "Face": "Yellow Eyegor",
   "Feet": "Bumblebees",
   "Hands": "Batboys",
   "Head": "Red Cap",
   "Item 1": "Blue Shovel",
   "Item 2": "Red Skate",
   "Outfit": "None",
   "Special": "None"
  }
 }
}