{
 "number": 139,
 "image_url": "https://algonfts.art/ALGUZQKNPJIU2GMACAMESXTAVBLGCJEVGAYCGZEMKWI4QRPKV3EDTTSQNM/1/1676048340714.webp",
 "metadata_cid": "bafkreigyb4x2n7siydghbbpgomkgkljbh6uvoad2lnin6atog2ogf4lnha",
 "metadata": {
  "name": "Algonean #0139",
  "standard": "arc3",
  "image": "ipfs://bafkreifizoeomu7i6nncpvfg6ahhaaxpyiznejg2aukm3lurcfvkgmycvy",
  "image_mime_type": "image/webp",
  "properties": {
   "Background": "Greenyellow",
   "Bodysuit": "Glossy Orange",
   "Face": "Dreamy",
   "Feet": "None",
   "Hands": "Sand",
   "Head": "White Headband",
   "Item 1": "None",
   "Item 2": "None",
   "Outfit": "None",
   "Special": "Black Cape"
  }
 }
}