{
 "number": 445,
 "image_url": "https://algonfts.art/ALGUZQKNPJIU2GMACAMESXTAVBLGCJEVGAYCGZEMKWI4QRPKV3EDTTSQNM/1/1676051052234.webp",
 "metadata_cid": "bafkreibhwru673uqvxlovw65gtrn52zo6pzcg2sihsnqeswokwxk226dmy",
 "metadata": {
  "name": "Algonean #0445",
  "standard": "arc3",
  "image": "ipfs://bafkreie2jibaieql7xazbsfytx3gwjy324huf44jpjxantao4zvjtz5tce",
  "image_mime_type": "image/webp",
  "properties": {
   "Background": "Main Dark",
   "Bodysuit": "Ultraviolet",
   "Face": "Happy Pink",
   "Feet": "Blue Dolls",
   "Hands": "Brown Grip",
   "Head": "Orange Shades",
   "Item 1": "Purple Potion",
   "Item 2": "Flashlight",
   "Outfit": "None",
   "Special": "None"
  }
 }
}