{
 "number": 466,
 "image_url": "https://algonfts.art/ALGUZQKNPJIU2GMACAMESXTAVBLGCJEVGAYCGZEMKWI4QRPKV3EDTTSQNM/1/1676051244032.webp",
 "metadata_cid": "bafkreiand45o37dfomqbeiky345ellcmjd3jsktle6miupo67w6g46gwwm",
 "metadata": {
  "name": "Algonean #0466",
  "standard": "arc3",
  "image": "ipfs://bafybeigoyka24ptgzh66jqyuzmxjtrabkwxjt5q2yk2bovva2wrl7tysky",
  "image_mime_type": "image/webp",
  "properties": {
   "Background": "Twisted Green",
   "Bodysuit": "Glossy Ice",
   "Face": "Serene Purple",
   "Feet": "None",
   "Hands": "Green",
   "Head": "None",
   "Item 1": "Chocolate Lolly",
   "Item 2": "None",
   "Outfit": "Blue Trooper",
   "Special": "None"
  }
 }
}