{
 "number": 472,
 "image_url": "https://algonfts.art/ALGUZQKNPJIU2GMACAMESXTAVBLGCJEVGAYCGZEMKWI4QRPKV3EDTTSQNM/1/1676051344993.webp",
 "metadata_cid": "bafkreifzryeytnxh46pxu5lqwjsfh6f3lypmz7jrjxah42qrzxp2jl55mu",
 "metadata": {
  "name": "Algonean #0472",
  "standard": "arc3",
  "image": "ipfs://bafkreib6cjawlij5wc4sse7jmiguqznsgbeaydpocpbmszo5jpivw3omsi",
  "image_mime_type": "image/webp",
  "properties": {
   "Background": "Tropical Mango",
   "Bodysuit": "Glossy Red",
   "Face": "Distressed Melon",
   "Feet": "Red Oldies",
   "Hands": "Mint",
   "Head": "Green Shades",
   "Item 1": "Drizzle GBoy",
   "Item 2": "Black Pennyboard",
   "Outfit": "Black Suit",
   "Special": "None"
  }
 }
}