{
 "number": 516,
 "image_url": "https://algonfts.art/ALGUZQKNPJIU2GMACAMESXTAVBLGCJEVGAYCGZEMKWI4QRPKV3EDTTSQNM/1/1676051712834.webp",
 "metadata_cid": "bafkreicst6un3xhsysc4sba2h6xoil4hsecal657mc2tjattjnchyievgy",
 "metadata": {
  "name": "Algonean #0516",
  "standard": "arc3",
  "image": "ipfs://bafybeigjuy7pjdxhz76xjza5rqlvccdua7v6zpis5euwqasjkzsrl2qtvi",
  "image_mime_type": "image/webp",
  "properties": {
   "Background": "Honeycomb",
   "Bodysuit": "Flint",
   "Face": "Happy Blue",
   "Feet": "Gray Workers",
   "Hands": "Grayscale",
   "Head": "Pink Meegy",
   "Item 1": "Apple Juice",
   "Item 2": "Blue Gamepad",
   "Outfit": "Red EVA",
   "Special": "None"
  }
 }
}