{
 "number": 592,
 "image_url": "https://algonfts.art/ALGUZQKNPJIU2GMACAMESXTAVBLGCJEVGAYCGZEMKWI4QRPKV3EDTTSQNM/1/1676052242261.webp",
 "metadata_cid": "bafkreicsl6fakabdrdecvew3untpibwieoxi5pn5r2bymy7utr6bhsss7u",
 "metadata": {
  "name": "Algonean #0592",
  "standard": "arc3",
  "image": "ipfs://bafkreihbj3m3jbdggijaz3oqbnk7pzbir3dmo3xmjs6v5pouk7v3xmcvze",
  "image_mime_type": "image/webp",
  "properties": {
   "Background": "Seafoam",
   "Bodysuit": "Bluewood",
   "Face": "Dull Green",
   "Feet": "Green Slippers",
   "Hands": "Orange",
   "Head": "Purple Horns",
   "Item 1": "None",
   "Item 2": "Red Bucket",
   "Outfit": "Red Beast",
   "Special": "None"
  }
 }
}