{
 "number": 659,
 "image_url": "https://algonfts.art/ALGUZQKNPJIU2GMACAMESXTAVBLGCJEVGAYCGZEMKWI4QRPKV3EDTTSQNM/1/1676052720257.webp",
 "metadata_cid": "bafkreigkc4x2pctm2eebpbqnke4vrqalkxlxoh4pn5oqd3db7tuygf3kxa",
 "metadata": {
  "name": "Algonean #0659",
  "standard": "arc3",
  "image": "ipfs://bafkreicvun5w7xiamqfrawo2m2kqzdm3r5bofcikkj76uqvaxweabw7ycu",
  "image_mime_type": "image/webp",
  "properties": {
   "Background": "Taffy",
   "Bodysuit": "Walnut",
   "Face": "Candy Skully",
   "Feet": "Yellow Oldies",
   "Hands": "Orange",
   "Head": "Violet Shades",
   "Item 1": "Blue Firecracker",
   "Item 2": "None",
   "Outfit": "Policeman",
   "Special": "None"
  }
 }
}