{
 "number": 747,
 "image_url": "https://algonfts.art/ALGUZQKNPJIU2GMACAMESXTAVBLGCJEVGAYCGZEMKWI4QRPKV3EDTTSQNM/1/1676053141695.webp",
 "metadata_cid": "bafkreihwl57jbavucwc3lwmspvs3ir4mcv6wxie6icjtoukko7i5b7nzkq",
 "metadata": {
  "name": "Algonean #0747",
  "standard": "arc3",
  "image": "ipfs://bafkreigdlmw2qy6xaywdrkfmsgscickfrpcvzlpmvibs33iuzwvoyt2taq",
  "image_mime_type": "image/webp",
  "properties": {
   "Background": "Purple Squiggle",
   "Bodysuit": "Worn Out Ocean",
   "Face": "Fed Up Gray",
   "Feet": "IcyHots",
   "Hands": "Blueo",
   "Head": "Blue Gumball",
   "Item 1": "Green Waterpistol",
   "Item 2": "Algorios",
   "Outfit": "Green Overall",
   "Special": "None"
  }
 }
}