{
 "number": 930,
 "image_url": "https://algonfts.art/ALGUZQKNPJIU2GMACAMESXTAVBLGCJEVGAYCGZEMKWI4QRPKV3EDTTSQNM/1/1676054592172.webp",
 "metadata_cid": "bafkreigq2qbjfdvq6qyyn7a5rb7ibwcej2vceju6nm4pyfjjf3xcsnsbre",
 "metadata": {
  "name": "Algonean #0930",
  "standard": "arc3",
  "image": "ipfs://bafkreigll4iomaoy3tijghtct2fvvkoycd6ouiq47zk4yywiqx35atj4se",
  "image_mime_type": "image/webp",
  "properties": {
   "Background": "Fresh Lemonade",
   "Bodysuit": "Dreamy Rainbow",
   "Face": "Catrina",
   "Feet": "Trek Shoes",
   "Hands": "Yellow",
   "Head": "Spartan",
   "Item 1": "Blue Potion",
   "Item 2": "Pink Paddleball",
   "Outfit": "Pink Bikini",
   "Special": "None"
  }
 }
}