{
 "number": 958,
 "image_url": "https://algonfts.art/ALGUZQKNPJIU2GMACAMESXTAVBLGCJEVGAYCGZEMKWI4QRPKV3EDTTSQNM/1/1676054820147.webp",
 "metadata_cid": "bafkreie4xvmuxw7turqvsahovvuhlmtuzezkahn5ugaxfkx5dhioi6pjye",
 "metadata": {
  "name": "Algonean #0958",
  "standard": "arc3",
  "image": "ipfs://bafkreidqxiktuvooabch5uiaje5q5siinys2v222qdvkae7jrelxi4h7n4",
  "image_mime_type": "image/webp",
  "properties": {
   "Background": "Main Black",
   "Bodysuit": "Gold",
   "Face": "Serene Dijon",
   "Feet": "Trek Shoes",
   "Hands": "Lavender",
   "Head": "Red Helmet",
   "Item 1": "Soda Bottle",
   "Item 2": "None",
   "Outfit": "Green Spacesuit",
   "Special": "None"
  }
 }
}